dict_typer/__init__.py
dict_typer/exceptions.py
dict_typer/models.py
dict_typer/type_definitions.py
dict_typer/utils.py
dict_typer-0.1.15.dist-info/entry_points.txt
dict_typer-0.1.15.dist-info/LICENSE
dict_typer-0.1.15.dist-info/WHEEL
dict_typer-0.1.15.dist-info/METADATA
dict_typer-0.1.15.dist-info/RECORD
